setup.py
Bayes_Infer/__init__.py
Bayes_Infer/sum-num.py
bayesinfer.egg-info/PKG-INFO
bayesinfer.egg-info/SOURCES.txt
bayesinfer.egg-info/dependency_links.txt
bayesinfer.egg-info/entry_points.txt
bayesinfer.egg-info/requires.txt
bayesinfer.egg-info/top_level.txt