Metadata-Version: 2.1
Name: bayesinfer
Version: 0.0.1
Summary: Automatically identify causal effects with Bayesian model.
Home-page: https://github.com/daixinyu/Bayes-infer
Author: tonydai
Author-email: 1320379472@qq.com
License: MIT
Keywords: python bayes inference event series
Platform: UNKNOWN
Classifier: Operating System :: OS Independent
Classifier: Topic :: Software Development
Classifier: Programming Language :: Python :: 3.6
Classifier: Programming Language :: Python :: Implementation :: PyPy
Provides-Extra: test
